{"stats":{"total":15,"passed":15},"status":"passed","newTests":[{"id":"ca7bbbd303a0b52fa3449a98f67847d7","name":"@negative scriptInput scenario","status":"passed","duration":4245},{"id":"df70b32e03c5e8ba5691608b5bb61e4d","name":"@negative invalidMobile scenario","status":"passed","duration":9274},{"id":"68526abb0a70a603e6e8a0a57aed09d3","name":"@negative emptyData scenario","status":"passed","duration":17600},{"id":"abe2cf37bd1f694d5d7cdd6cac0fac13","name":"@negative invalidMobile scenario","status":"passed","duration":15040},{"id":"aafc63c6e9cc2d89e8757b9881570944","name":"@positive Valid User Registration","status":"passed","duration":7647},{"id":"8ba70e53fe21ee6751702d514547f69e","name":"@negative scriptInput scenario","status":"passed","duration":6457},{"id":"24a29d94e4f218cfccf33018c648b843","name":"@negative invalidMobile scenario","status":"passed","duration":4839},{"id":"ea78993acb7f7bde31aacba3002bc5d5","name":"@negative symbolInput scenario","status":"passed","duration":3738},{"id":"d9e57e0cb47a83aa50492ac9dc7f4643","name":"@negative emptyData scenario","status":"passed","duration":4496},{"id":"36e3472bfad427addd8733aebb76ab92","name":"@negative symbolInput scenario","status":"passed","duration":6883},{"id":"85d932fe04d5e3600c853a9558d60696","name":"@positive Valid User Registration","status":"passed","duration":4305},{"id":"ab0fba9a8620e763a0c5dfbd49b47858","name":"@negative emptyData scenario","status":"passed","duration":8505},{"id":"4d0aefbdb7c025cf2985350af672c145","name":"@positive Valid User Registration","status":"passed","duration":17702},{"id":"9eb1ec4dc7031570f7f7d36204d11bf5","name":"@negative scriptInput scenario","status":"passed","duration":5875},{"id":"706da5022bda508a63268810e0c1a56b","name":"@negative symbolInput scenario","status":"passed","duration":6582}],"flakyTests":[],"retryTests":[],"name":"Allure Report","duration":123188,"createdAt":1775190705835,"plugin":"Awesome","meta":{"reportId":"279a05df-5042-4398-b8b8-11d55da1a3bf","singleFile":false,"withTestResultsLinks":true},"pullRequestHref":"","jobHref":"https://github.com/fakhrezasusilos/automation_test/actions/runs/23933823237"}