{"stats":{"total":15,"passed":15},"status":"passed","newTests":[{"id":"b94b8aac8cdc6e37b8511d8528897946","name":"@negative scriptInput scenario","status":"passed","duration":3436},{"id":"8cac13533fd5ba4aa1ffbe62b494df1d","name":"@negative emptyData scenario","status":"passed","duration":8954},{"id":"b0044e51ee9907b39c1cd09f76940646","name":"@negative symbolInput scenario","status":"passed","duration":5201},{"id":"7932bac9a8bce9ff4fa0ff5321cbf4fd","name":"@negative invalidMobile scenario","status":"passed","duration":15265},{"id":"80d3108da981d3cf0c5a9f7129d055db","name":"@negative invalidMobile scenario","status":"passed","duration":17664},{"id":"3cf420fa50a2c1f3ff268a151197ac5a","name":"@negative scriptInput scenario","status":"passed","duration":5504},{"id":"23ae1c835ea826e61417383b3be893f1","name":"@positive Valid User Registration","status":"passed","duration":8031},{"id":"9ec0caac6efd0385aa56c723bfcf11ee","name":"@negative symbolInput scenario","status":"passed","duration":8107},{"id":"12b9e1df882c4aedac8d80fef8ed5663","name":"@negative emptyData scenario","status":"passed","duration":4257},{"id":"c841cfe6b7821c6eda243ef29897b40b","name":"@negative symbolInput scenario","status":"passed","duration":3127},{"id":"b4c131b058336619a4dfb01114f395c3","name":"@negative invalidMobile scenario","status":"passed","duration":3946},{"id":"f64624b0156dd41b2ead281340a54fa2","name":"@negative scriptInput scenario","status":"passed","duration":7228},{"id":"0ffe876cbec33f47190172eaacccc5cc","name":"@positive Valid User Registration","status":"passed","duration":17929},{"id":"3095b5977321580d80932cfd136cd720","name":"@positive Valid User Registration","status":"passed","duration":4168},{"id":"4213bfad25a7dc07b3addbd523406449","name":"@negative emptyData scenario","status":"passed","duration":17874}],"flakyTests":[],"retryTests":[],"name":"Allure Report","duration":130691,"createdAt":1773894306576,"plugin":"Awesome","meta":{"reportId":"0c647e9b-f29b-4f4a-80b0-eecbc97d32a6","singleFile":false,"withTestResultsLinks":true},"pullRequestHref":"","jobHref":"https://github.com/fakhrezasusilos/automation_test/actions/runs/23279720340"}